epiccli/__init__.py
epiccli/_version.py
epiccli/billing.py
epiccli/catalog.py
epiccli/data.py
epiccli/job.py
epiccli/main.py
epiccli/project.py
epiccli/requirements.txt
epiccli/ui.py
epiccli/user.py
epiccli_lite-0.4.1.dist-info/licenses/LICENSE
epiccli_ui/__init__.py
epiccli_ui/app.py
epiccli_ui/requirements.txt
epiccli_ui/static/logo.png
epiccli_ui/static/logo2.png
epiccli_ui/static/style.css
epiccli_ui/static/vtk.js
epiccli_ui/static/vtk.js.map
epiccli_ui/static/zenotech.png
epiccli_ui/templates/dashboard.html
epiccli_ui/templates/index.html
epiccli_lite-0.4.1.dist-info/METADATA
epiccli_lite-0.4.1.dist-info/WHEEL
epiccli_lite-0.4.1.dist-info/entry_points.txt
epiccli_lite-0.4.1.dist-info/top_level.txt
epiccli_lite-0.4.1.dist-info/RECORD
