Metadata-Version: 2.4
Name: epiccli-lite
Version: 0.4.1
Summary: A CLI for the EPIC API
Home-page: https://github.com/zenotech/epic-cli
Author: Zenotech Ltd
Author-email: support@zenotech.com
Classifier: Programming Language :: Python :: 3
Classifier: License :: OSI Approved :: MIT License
Classifier: Operating System :: OS Independent
Requires-Python: >=3.6
License-File: LICENSE
Requires-Dist: boto3
Requires-Dist: PyQt5; sys_platform == "linux"
Requires-Dist: qtpy; sys_platform == "linux"
Requires-Dist: Flask
Requires-Dist: pywebview
Requires-Dist: pyqtwebengine; sys_platform == "linux"
Requires-Dist: reportlab
Requires-Dist: click
Requires-Dist: requests
Dynamic: author
Dynamic: author-email
Dynamic: classifier
Dynamic: description
Dynamic: description-content-type
Dynamic: home-page
Dynamic: license-file
Dynamic: requires-dist
Dynamic: requires-python
Dynamic: summary
